manticoresearch/__init__.py
manticoresearch/api_client.py
manticoresearch/api_response.py
manticoresearch/configuration.py
manticoresearch/exceptions.py
manticoresearch/py.typed
manticoresearch/rest.py
manticoresearch/api/__init__.py
manticoresearch/api/index_api.py
manticoresearch/api/search_api.py
manticoresearch/api/utils_api.py
manticoresearch/models/__init__.py
manticoresearch/models/agg_composite.py
manticoresearch/models/agg_composite_source.py
manticoresearch/models/agg_composite_term.py
manticoresearch/models/agg_date_histogram.py
manticoresearch/models/agg_histogram.py
manticoresearch/models/agg_terms.py
manticoresearch/models/aggregation.py
manticoresearch/models/autocomplete_request.py
manticoresearch/models/bool_filter.py
manticoresearch/models/bulk_response.py
manticoresearch/models/delete_document_request.py
manticoresearch/models/delete_response.py
manticoresearch/models/error_response.py
manticoresearch/models/fulltext_filter.py
manticoresearch/models/geo_distance.py
manticoresearch/models/geo_distance_location_anchor.py
manticoresearch/models/highlight.py
manticoresearch/models/highlight_field_option.py
manticoresearch/models/highlight_fields.py
manticoresearch/models/hits_hits.py
manticoresearch/models/insert_document_request.py
manticoresearch/models/join.py
manticoresearch/models/join_cond.py
manticoresearch/models/join_on.py
manticoresearch/models/knn.py
manticoresearch/models/knn_query.py
manticoresearch/models/match.py
manticoresearch/models/match_all.py
manticoresearch/models/percolate_request.py
manticoresearch/models/percolate_request_query.py
manticoresearch/models/query_filter.py
manticoresearch/models/range.py
manticoresearch/models/replace_document_request.py
manticoresearch/models/response_error.py
manticoresearch/models/response_error_details.py
manticoresearch/models/search_query.py
manticoresearch/models/search_request.py
manticoresearch/models/search_response.py
manticoresearch/models/search_response_hits.py
manticoresearch-10.0.2.dist-info/licenses/LICENSE.txt
manticoresearch-10.0.2.dist-info/METADATA
manticoresearch-10.0.2.dist-info/WHEEL
manticoresearch-10.0.2.dist-info/top_level.txt
manticoresearch-10.0.2.dist-info/RECORD
