Metadata-Version: 2.4
Name: manticoresearch
Version: 10.0.2
Summary: Manticore Search Client
Home-page: 
Author: Manticore Software Ltd.
Author-email: "Manticore Software Ltd." <info@manticoresearch.com>
License: MIT
Project-URL: Repository, https://github.com/manticoresoftware/manticoresearch-python
Keywords: OpenAPI,OpenAPI-Generator,Manticore Search Client
Requires-Python: >=3.9
License-File: LICENSE.txt
Requires-Dist: urllib3<3.0.0,>=2.1.0
Requires-Dist: python-dateutil>=2.8.2
Requires-Dist: pydantic>=2
Requires-Dist: typing-extensions>=4.7.1
Dynamic: author
Dynamic: license-file
